htbuilder/__init__.py
htbuilder/funcs.py
htbuilder/units.py
htbuilder/utils.py
htbuilder-0.6.2.dist-info/LICENSE
htbuilder-0.6.2.dist-info/METADATA
htbuilder-0.6.2.dist-info/WHEEL
htbuilder-0.6.2.dist-info/top_level.txt
htbuilder-0.6.2.dist-info/RECORD
