Metadata-Version: 2.1
Name: htbuilder
Version: 0.6.2
Summary: A purely-functional HTML builder for Python. Think JSX rather than templates.
Home-page: https://github.com/tvst/htbuilder
Author: Thiago Teixeira
Author-email: me@thiagot.com
License: Apache 2
Classifier: Programming Language :: Python :: 3
Classifier: License :: OSI Approved :: Apache Software License
Classifier: Operating System :: OS Independent
Requires-Python: >=3.5
License-File: LICENSE
